{
    "spread": "3m10y",
    "prediction_type": "next_day",
    "model_type": "xgb",
    "num_features": 290,
    "selected_features": [
        "10s30s Spread_zscore_63d",
        "5s30s Spread_rsi_63d",
        "3-Year_pct_change_63d",
        "2-Year_dist_ma_5d",
        "10s30s Spread_zscore_21d",
        "2s10s Spread_vol_63d",
        "5-Year_vol_63d",
        "2s5s Spread_dist_ma_21d",
        "6-Month_vol_10d",
        "5s30s Spread_vol_126d",
        "3m10y Spread_zscore_252d",
        "3-Month_zscore_63d",
        "5s30s Spread_pct_change_21d",
        "3-Month_pct_change_5d",
        "3-Year_zscore_21d",
        "2s5s Spread_vol_10d",
        "1-Year_dist_ma_10d",
        "5s30s Spread_rsi_5d",
        "3-Year_zscore_5d",
        "10s30s Spread_change_126d",
        "2-Year_dist_ma_21d",
        "10s30s Spread_rsi_63d",
        "6-Month_dist_ma_10d",
        "10s30s Spread_vol_126d",
        "3m10y Spread_zscore_63d",
        "day_of_week",
        "10s30s Spread_vol_10d",
        "10s30s Spread_zscore_252d",
        "3m10y Spread_vol_126d",
        "20-Year_vol_10d",
        "6-Month_zscore_126d",
        "5s30s Spread_dist_ma_252d",
        "2s10s Spread_dist_ma_10d",
        "2s10s Spread_pct_change_10d",
        "2s5s Spread_vol_21d",
        "10s30s Spread_change_1d",
        "10s30s Spread_vol_5d",
        "6-Month_vol_5d",
        "5s30s Spread_rsi_21d",
        "1-Year_zscore_252d",
        "3-Month_vol_63d",
        "2s10s Spread_change_5d",
        "6-Month_pct_change_21d",
        "2s10s Spread_dist_ma_5d",
        "yield_pc3_curvature",
        "3m10y Spread_change_63d",
        "3-Year_dist_ma_5d",
        "3-Month_change_10d",
        "2s10s Spread_rsi_10d",
        "10s30s Spread_rsi_21d",
        "2s5s Spread_vol_63d",
        "5-Year_vol_252d",
        "1-Year_zscore_21d",
        "3m10y Spread_dist_ma_63d",
        "2s10s Spread_dist_ma_126d",
        "3-Month_pct_change_21d",
        "1-Year_zscore_126d",
        "1-Year_vol_10d",
        "3m10y Spread_dist_ma_21d",
        "3-Month_vol_5d",
        "1-Year_pct_change_10d",
        "1-Year_zscore_10d",
        "5-Year_zscore_5d",
        "3m10y Spread_pct_change_1d",
        "5s30s Spread_dist_ma_5d",
        "2-Year_pct_change_1d",
        "1-Year_vol_5d",
        "2s10s Spread_dist_ma_63d",
        "5-Year_pct_change_5d",
        "6-Month_pct_change_5d",
        "2s10s Spread_zscore_252d",
        "2-Year_pct_change_21d",
        "3m10y Spread_pct_change_21d",
        "5-Year_vol_21d",
        "2-Year_vol_10d",
        "2s5s Spread_dist_ma_5d",
        "10s30s Spread_dist_ma_252d",
        "3-Month_rsi_5d",
        "5-Year_rsi_5d",
        "3-Year_pct_change_1d",
        "5s30s Spread_dist_ma_21d",
        "6-Month_dist_ma_21d",
        "10s30s Spread_rsi_5d",
        "3-Month_zscore_126d",
        "1-Year_pct_change_1d",
        "3m10y Spread_dist_ma_5d",
        "1-Year_pct_change_63d",
        "3m10y Spread_change_21d",
        "3-Month_pct_change_1d",
        "5-Year_pct_change_21d",
        "2s5s Spread_pct_change_1d",
        "2s5s Spread_vol_5d",
        "5s30s Spread_zscore_252d",
        "5s30s Spread_change_5d",
        "3-Month_zscore_5d",
        "3m10y Spread_change_1d",
        "2-Year_vol_126d",
        "5s30s Spread_dist_ma_63d",
        "6-Month_vol_21d",
        "5s30s Spread_change_1d",
        "10s30s Spread_pct_change_5d",
        "5-Year_pct_change_63d",
        "2s5s Spread_pct_change_10d",
        "2s10s Spread_rsi_21d",
        "2s10s Spread_change_1d",
        "2s10s Spread_pct_change_1d",
        "2s10s Spread_zscore_21d",
        "2s5s Spread_rsi_21d",
        "3-Year_zscore_10d",
        "5s30s Spread_zscore_126d",
        "2-Year_pct_change_10d",
        "2s10s Spread_dist_ma_252d",
        "10s30s Spread_change_21d",
        "10s30s Spread_zscore_126d",
        "3-Month_pct_change_10d",
        "2s10s Spread_vol_10d",
        "3-Month_rsi_21d",
        "5s30s Spread_pct_change_126d",
        "2s5s Spread_dist_ma_126d",
        "2s5s Spread_pct_change_21d",
        "5s30s Spread_zscore_5d",
        "10s30s Spread_pct_change_63d",
        "10s30s Spread_rsi_10d",
        "1-Year_zscore_5d",
        "1-Year_rsi_21d",
        "2s5s Spread_rsi_10d",
        "1-Year_pct_change_21d",
        "3m10y Spread_vol_5d",
        "day_of_month",
        "1-Year_dist_ma_5d",
        "2s10s Spread_zscore_10d",
        "3m10y Spread_vol_10d",
        "2s5s Spread_vol_252d",
        "5s30s Spread_change_63d",
        "3-Year_vol_5d",
        "3m10y Spread_rsi_21d",
        "2s5s Spread_change_5d",
        "5-Year_change_1d",
        "3-Year_pct_change_126d",
        "20-Year_vol_5d",
        "5s30s Spread_vol_63d",
        "5s30s Spread_vol_21d",
        "1-Year_vol_21d",
        "5-Year_pct_change_10d",
        "2s10s Spread_pct_change_21d",
        "2-Year_rsi_10d",
        "3m10y Spread_change_252d",
        "6-Month_dist_ma_5d",
        "3m10y Spread_pct_change_10d",
        "2s10s Spread_vol_126d",
        "2s10s Spread_change_21d",
        "3m10y Spread_change_5d",
        "1-Year_pct_change_5d",
        "3-Month_zscore_21d",
        "3m10y Spread_pct_change_5d",
        "3-Month_dist_ma_21d",
        "2-Year_zscore_252d",
        "6-Month_pct_change_10d",
        "2-Year_vol_5d",
        "5-Year_rsi_10d",
        "1-Year_dist_ma_21d",
        "2s10s Spread_change_10d",
        "2-Year_zscore_21d",
        "10s30s Spread_zscore_10d",
        "5s30s Spread_dist_ma_10d",
        "2-Year_zscore_126d",
        "2s10s Spread_dist_ma_21d",
        "5s30s Spread_pct_change_10d",
        "6-Month_rsi_10d",
        "5-Year_vol_126d",
        "2-Year_rsi_63d",
        "3-Month_zscore_252d",
        "2-Year_rsi_126d",
        "3-Month_rsi_126d",
        "3-Year_change_1d",
        "2s5s Spread_change_10d",
        "10s30s Spread_pct_change_21d",
        "2s5s Spread_zscore_21d",
        "10s30s Spread_vol_21d",
        "2s5s Spread_pct_change_5d",
        "10s30s Spread_dist_ma_126d",
        "1-Year_vol_63d",
        "2s5s Spread_vol_126d",
        "6-Month_zscore_21d",
        "6-Month_pct_change_1d",
        "3-Month_rsi_63d",
        "2s10s Spread_change_252d",
        "3-Month_dist_ma_5d",
        "3m10y Spread_ma_1d",
        "10s30s Spread_change_63d",
        "3-Month_vol_10d",
        "6-Month_zscore_63d",
        "2s10s Spread_pct_change_5d",
        "3-Month_vol_126d",
        "5s30s Spread_pct_change_1d",
        "10s30s Spread_dist_ma_63d",
        "2s5s Spread_dist_ma_252d",
        "10s30s Spread_pct_change_126d",
        "2s10s Spread_zscore_5d",
        "2-Year_dist_ma_10d",
        "3m10y Spread_vol_63d",
        "2-Year_vol_63d",
        "2-Year_vol_21d",
        "6-Month_change_1d",
        "2-Year_pct_change_63d",
        "5s30s Spread_change_21d",
        "1-Year_zscore_63d",
        "3-Month_change_5d",
        "1-Year_rsi_5d",
        "3-Year_pct_change_21d",
        "yield_pc2_slope",
        "2s10s Spread_vol_5d",
        "2s5s Spread_change_252d",
        "3m10y Spread_zscore_21d",
        "5-Year_pct_change_1d",
        "5s30s Spread_dist_ma_126d",
        "3-Month_rsi_10d",
        "5s30s Spread_pct_change_63d",
        "2s5s Spread_dist_ma_10d",
        "5s30s Spread_vol_10d",
        "3-Year_pct_change_5d",
        "5s30s Spread_change_10d",
        "5s30s Spread_pct_change_5d",
        "1-Year_rsi_63d",
        "20-Year_vol_21d",
        "3m10y Spread_zscore_5d",
        "6-Month_rsi_5d",
        "5s30s Spread_rsi_10d",
        "2-Year_dist_ma_63d",
        "5-Year_vol_5d",
        "2s5s Spread_change_1d",
        "2-Year_change_1d",
        "2-Year_change_10d",
        "2-Year_rsi_21d",
        "10s30s Spread_dist_ma_21d",
        "3m10y Spread_rsi_5d",
        "2s5s Spread_dist_ma_63d",
        "3m10y Spread_zscore_10d",
        "2s10s Spread_zscore_126d",
        "is_day_before_holiday",
        "2s5s Spread_pct_change_63d",
        "3m10y Spread_rsi_10d",
        "3-Month_dist_ma_10d",
        "10s30s Spread_zscore_5d",
        "10s30s Spread_dist_ma_10d",
        "5-Year_vol_10d",
        "6-Month_zscore_10d",
        "6-Month_rsi_63d",
        "2s10s Spread_zscore_63d",
        "2s10s Spread_pct_change_63d",
        "2s5s Spread_zscore_63d",
        "2-Year_pct_change_5d",
        "3-Month_zscore_10d",
        "10s30s Spread_vol_252d",
        "2s5s Spread_zscore_126d",
        "2-Year_zscore_63d",
        "10s30s Spread_dist_ma_5d",
        "2s5s Spread_rsi_5d",
        "3-Year_rsi_10d",
        "3-Year_rsi_5d",
        "2-Year_zscore_5d",
        "5s30s Spread_zscore_63d",
        "5s30s Spread_zscore_21d",
        "3m10y Spread_vol_21d",
        "5s30s Spread_zscore_10d",
        "10s30s Spread_pct_change_252d",
        "10s30s Spread_pct_change_1d",
        "2s10s Spread_vol_21d",
        "6-Month_zscore_5d",
        "3m10y Spread_change_10d",
        "5s30s Spread_change_126d",
        "3m10y Spread_vol_252d",
        "10s30s Spread_change_5d",
        "5s30s Spread_vol_5d",
        "6-Month_rsi_21d",
        "1-Year_rsi_10d",
        "5-Year_zscore_10d",
        "3-Year_pct_change_10d",
        "2s10s Spread_rsi_5d",
        "2-Year_change_5d",
        "2-Year_zscore_10d",
        "10s30s Spread_vol_63d",
        "10s30s Spread_pct_change_10d",
        "1-Year_change_1d",
        "3m10y Spread_dist_ma_10d",
        "2s5s Spread_zscore_5d",
        "2s5s Spread_change_126d",
        "2s5s Spread_zscore_10d",
        "2-Year_rsi_5d",
        "3-Month_vol_21d"
    ],
    "mse": [
        37.40012417349221,
        32.45643895373438,
        26.671465517519437,
        42.16116814620537,
        56.03583508501688
    ],
    "accuracy": null,
    "f1": null,
    "roc_auc": null,
    "feature_importance": {
        "10s30s Spread_zscore_63d": 0.00041413912549614906,
        "5s30s Spread_rsi_63d": 0.0008708761888556182,
        "3-Year_pct_change_63d": 0.0007654853980056942,
        "2-Year_dist_ma_5d": 0.0014280820032581687,
        "10s30s Spread_zscore_21d": 0.0009289684821851552,
        "2s10s Spread_vol_63d": 0.001530644716694951,
        "5-Year_vol_63d": 0.0021359629463404417,
        "2s5s Spread_dist_ma_21d": 0.00153911963570863,
        "6-Month_vol_10d": 0.003393827471882105,
        "5s30s Spread_vol_126d": 0.0013320929137989879,
        "3m10y Spread_zscore_252d": 0.001421264372766018,
        "3-Month_zscore_63d": 0.002139309886842966,
        "5s30s Spread_pct_change_21d": 0.0022685970179736614,
        "3-Month_pct_change_5d": 0.002911400981247425,
        "3-Year_zscore_21d": 0.0015779737150296569,
        "2s5s Spread_vol_10d": 0.0019705663435161114,
        "1-Year_dist_ma_10d": 0.002223087940365076,
        "5s30s Spread_rsi_5d": 0.001523815793916583,
        "3-Year_zscore_5d": 0.0024685407988727093,
        "10s30s Spread_change_126d": 0.006466159131377935,
        "2-Year_dist_ma_21d": 0.002238381654024124,
        "10s30s Spread_rsi_63d": 0.002474034670740366,
        "6-Month_dist_ma_10d": 0.0024208570830523968,
        "10s30s Spread_vol_126d": 0.002108105458319187,
        "3m10y Spread_zscore_63d": 0.0023326913360506296,
        "day_of_week": 0.0048454878851771355,
        "10s30s Spread_vol_10d": 0.0018337375950068235,
        "10s30s Spread_zscore_252d": 0.0027056958060711622,
        "3m10y Spread_vol_126d": 0.004131099674850702,
        "20-Year_vol_10d": 0.002573213540017605,
        "6-Month_zscore_126d": 0.002540344838052988,
        "5s30s Spread_dist_ma_252d": 0.002062996616587043,
        "2s10s Spread_dist_ma_10d": 0.002852517878636718,
        "2s10s Spread_pct_change_10d": 0.0023712418042123318,
        "2s5s Spread_vol_21d": 0.0027190688997507095,
        "10s30s Spread_change_1d": 0.002212421502918005,
        "10s30s Spread_vol_5d": 0.0045045409351587296,
        "6-Month_vol_5d": 0.0032628350891172886,
        "5s30s Spread_rsi_21d": 0.0014107904862612486,
        "1-Year_zscore_252d": 0.002956903073936701,
        "3-Month_vol_63d": 0.0026474534533917904,
        "2s10s Spread_change_5d": 0.006870250217616558,
        "6-Month_pct_change_21d": 0.0019982389640063047,
        "2s10s Spread_dist_ma_5d": 0.0010544240940362215,
        "yield_pc3_curvature": 0.0028002248145639896,
        "3m10y Spread_change_63d": 0.00571780139580369,
        "3-Year_dist_ma_5d": 0.00492385309189558,
        "3-Month_change_10d": 0.004405119922012091,
        "2s10s Spread_rsi_10d": 0.0038365013897418976,
        "10s30s Spread_rsi_21d": 0.002159645315259695,
        "2s5s Spread_vol_63d": 0.0044725071638822556,
        "5-Year_vol_252d": 0.0020571008790284395,
        "1-Year_zscore_21d": 0.0033176648430526257,
        "3m10y Spread_dist_ma_63d": 0.008745834231376648,
        "2s10s Spread_dist_ma_126d": 0.0016889506950974464,
        "3-Month_pct_change_21d": 0.004170685540884733,
        "1-Year_zscore_126d": 0.00589345395565033,
        "1-Year_vol_10d": 0.0013797886203974485,
        "3m10y Spread_dist_ma_21d": 0.0038106292486190796,
        "3-Month_vol_5d": 0.0013618896482512355,
        "1-Year_pct_change_10d": 0.0038833122234791517,
        "1-Year_zscore_10d": 0.0031653023324906826,
        "5-Year_zscore_5d": 0.002581103704869747,
        "3m10y Spread_pct_change_1d": 0.002765561453998089,
        "5s30s Spread_dist_ma_5d": 0.003180580912157893,
        "2-Year_pct_change_1d": 0.0028912427369505167,
        "1-Year_vol_5d": 0.001659289700910449,
        "2s10s Spread_dist_ma_63d": 0.003742226865142584,
        "5-Year_pct_change_5d": 0.0020526174921542406,
        "6-Month_pct_change_5d": 0.003005949081853032,
        "2s10s Spread_zscore_252d": 0.0015827326569706202,
        "2-Year_pct_change_21d": 0.0018409481272101402,
        "3m10y Spread_pct_change_21d": 0.002532190177589655,
        "5-Year_vol_21d": 0.0035994485951960087,
        "2-Year_vol_10d": 0.0031702942214906216,
        "2s5s Spread_dist_ma_5d": 0.001390458201058209,
        "10s30s Spread_dist_ma_252d": 0.0018176070880144835,
        "3-Month_rsi_5d": 0.001805230975151062,
        "5-Year_rsi_5d": 0.005136957857757807,
        "3-Year_pct_change_1d": 0.0045736501924693584,
        "5s30s Spread_dist_ma_21d": 0.013233627192676067,
        "6-Month_dist_ma_21d": 0.005119450856000185,
        "10s30s Spread_rsi_5d": 0.003451986238360405,
        "3-Month_zscore_126d": 0.0023596484679728746,
        "1-Year_pct_change_1d": 0.003869233187288046,
        "3m10y Spread_dist_ma_5d": 0.002820756286382675,
        "1-Year_pct_change_63d": 0.003474058583378792,
        "3m10y Spread_change_21d": 0.002528296783566475,
        "3-Month_pct_change_1d": 0.00245373765937984,
        "5-Year_pct_change_21d": 0.0026458832435309887,
        "2s5s Spread_pct_change_1d": 0.0033330090809613466,
        "2s5s Spread_vol_5d": 0.0026591322384774685,
        "5s30s Spread_zscore_252d": 0.005921504460275173,
        "5s30s Spread_change_5d": 0.004231598228216171,
        "3-Month_zscore_5d": 0.0021956623531877995,
        "3m10y Spread_change_1d": 0.0038505711127072573,
        "2-Year_vol_126d": 0.00474341306835413,
        "5s30s Spread_dist_ma_63d": 0.002393511589616537,
        "6-Month_vol_21d": 0.0036729727871716022,
        "5s30s Spread_change_1d": 0.0034750259947031736,
        "10s30s Spread_pct_change_5d": 0.0036179337184876204,
        "5-Year_pct_change_63d": 0.0021824196446686983,
        "2s5s Spread_pct_change_10d": 0.0032530378084629774,
        "2s10s Spread_rsi_21d": 0.001972926314920187,
        "2s10s Spread_change_1d": 0.005888794548809528,
        "2s10s Spread_pct_change_1d": 0.0029640025459229946,
        "2s10s Spread_zscore_21d": 0.0014351143036037683,
        "2s5s Spread_rsi_21d": 0.004700173623859882,
        "3-Year_zscore_10d": 0.003486162517219782,
        "5s30s Spread_zscore_126d": 0.00286132306791842,
        "2-Year_pct_change_10d": 0.003283460158854723,
        "2s10s Spread_dist_ma_252d": 0.009909473359584808,
        "10s30s Spread_change_21d": 0.008139332756400108,
        "10s30s Spread_zscore_126d": 0.003000375349074602,
        "3-Month_pct_change_10d": 0.002477400004863739,
        "2s10s Spread_vol_10d": 0.002179046394303441,
        "3-Month_rsi_21d": 0.004927624948322773,
        "5s30s Spread_pct_change_126d": 0.004175073467195034,
        "2s5s Spread_dist_ma_126d": 0.0025048598181456327,
        "2s5s Spread_pct_change_21d": 0.004584477283060551,
        "5s30s Spread_zscore_5d": 0.004803651012480259,
        "10s30s Spread_pct_change_63d": 0.003059892449527979,
        "10s30s Spread_rsi_10d": 0.004163976758718491,
        "1-Year_zscore_5d": 0.002737759379670024,
        "1-Year_rsi_21d": 0.003088501049205661,
        "2s5s Spread_rsi_10d": 0.00426872493699193,
        "1-Year_pct_change_21d": 0.0018452685326337814,
        "3m10y Spread_vol_5d": 0.0018243513768538833,
        "day_of_month": 0.003738701343536377,
        "1-Year_dist_ma_5d": 0.0030171878170222044,
        "2s10s Spread_zscore_10d": 0.00275855278596282,
        "3m10y Spread_vol_10d": 0.004157043993473053,
        "2s5s Spread_vol_252d": 0.004149426706135273,
        "5s30s Spread_change_63d": 0.004209207836538553,
        "3-Year_vol_5d": 0.002389450091868639,
        "3m10y Spread_rsi_21d": 0.003671022830531001,
        "2s5s Spread_change_5d": 0.0022830963134765625,
        "5-Year_change_1d": 0.005027879029512405,
        "3-Year_pct_change_126d": 0.003275476396083832,
        "20-Year_vol_5d": 0.0023594789672642946,
        "5s30s Spread_vol_63d": 0.005231463350355625,
        "5s30s Spread_vol_21d": 0.004217576235532761,
        "1-Year_vol_21d": 0.002604244276881218,
        "5-Year_pct_change_10d": 0.004795805085450411,
        "2s10s Spread_pct_change_21d": 0.004251661244779825,
        "2-Year_rsi_10d": 0.005166667979210615,
        "3m10y Spread_change_252d": 0.007597572170197964,
        "6-Month_dist_ma_5d": 0.002497010165825486,
        "3m10y Spread_pct_change_10d": 0.003381164278835058,
        "2s10s Spread_vol_126d": 0.003878213930875063,
        "2s10s Spread_change_21d": 0.004805289208889008,
        "3m10y Spread_change_5d": 0.0026998098473995924,
        "1-Year_pct_change_5d": 0.005692732520401478,
        "3-Month_zscore_21d": 0.002760577481240034,
        "3m10y Spread_pct_change_5d": 0.002126092556864023,
        "3-Month_dist_ma_21d": 0.002698544878512621,
        "2-Year_zscore_252d": 0.003425728064030409,
        "6-Month_pct_change_10d": 0.0011428806465119123,
        "2-Year_vol_5d": 0.0024901540018618107,
        "5-Year_rsi_10d": 0.006319726351648569,
        "1-Year_dist_ma_21d": 0.0016561830416321754,
        "2s10s Spread_change_10d": 0.0032009147107601166,
        "2-Year_zscore_21d": 0.0021682775113731623,
        "10s30s Spread_zscore_10d": 0.0019136958289891481,
        "5s30s Spread_dist_ma_10d": 0.004117841366678476,
        "2-Year_zscore_126d": 0.0024642907083034515,
        "2s10s Spread_dist_ma_21d": 0.003487913403660059,
        "5s30s Spread_pct_change_10d": 0.0028255104552954435,
        "6-Month_rsi_10d": 0.001991631928831339,
        "5-Year_vol_126d": 0.0023818141780793667,
        "2-Year_rsi_63d": 0.005778969265520573,
        "3-Month_zscore_252d": 0.0022846730425953865,
        "2-Year_rsi_126d": 0.003911040257662535,
        "3-Month_rsi_126d": 0.00222528213635087,
        "3-Year_change_1d": 0.0016849454259499907,
        "2s5s Spread_change_10d": 0.0009407275356352329,
        "10s30s Spread_pct_change_21d": 0.0022698871325701475,
        "2s5s Spread_zscore_21d": 0.002252188976854086,
        "10s30s Spread_vol_21d": 0.004542163107544184,
        "2s5s Spread_pct_change_5d": 0.002920042257755995,
        "10s30s Spread_dist_ma_126d": 0.006658506579697132,
        "1-Year_vol_63d": 0.0031811967492103577,
        "2s5s Spread_vol_126d": 0.003816864686086774,
        "6-Month_zscore_21d": 0.002401683945208788,
        "6-Month_pct_change_1d": 0.003257233649492264,
        "3-Month_rsi_63d": 0.005033926106989384,
        "2s10s Spread_change_252d": 0.0021113543771207333,
        "3-Month_dist_ma_5d": 0.004799959249794483,
        "3m10y Spread_ma_1d": 0.0029159002006053925,
        "10s30s Spread_change_63d": 0.005673346109688282,
        "3-Month_vol_10d": 0.003970687743276358,
        "6-Month_zscore_63d": 0.005984652787446976,
        "2s10s Spread_pct_change_5d": 0.003231919603422284,
        "3-Month_vol_126d": 0.002792125102132559,
        "5s30s Spread_pct_change_1d": 0.005143828224390745,
        "10s30s Spread_dist_ma_63d": 0.004764608573168516,
        "2s5s Spread_dist_ma_252d": 0.0025700547266751528,
        "10s30s Spread_pct_change_126d": 0.005624555982649326,
        "2s10s Spread_zscore_5d": 0.003122725524008274,
        "2-Year_dist_ma_10d": 0.002909960923716426,
        "3m10y Spread_vol_63d": 0.0040239752270281315,
        "2-Year_vol_63d": 0.009159479290246964,
        "2-Year_vol_21d": 0.002092722337692976,
        "6-Month_change_1d": 0.0020147988107055426,
        "2-Year_pct_change_63d": 0.003647956531494856,
        "5s30s Spread_change_21d": 0.011386865749955177,
        "1-Year_zscore_63d": 0.0040664225816726685,
        "3-Month_change_5d": 0.006120243109762669,
        "1-Year_rsi_5d": 0.0024955321568995714,
        "3-Year_pct_change_21d": 0.004845094867050648,
        "yield_pc2_slope": 0.0034474977292120457,
        "2s10s Spread_vol_5d": 0.0028142256196588278,
        "2s5s Spread_change_252d": 0.003803655505180359,
        "3m10y Spread_zscore_21d": 0.00349107151851058,
        "5-Year_pct_change_1d": 0.0026609457563608885,
        "5s30s Spread_dist_ma_126d": 0.003463123459368944,
        "3-Month_rsi_10d": 0.003528709290549159,
        "5s30s Spread_pct_change_63d": 0.00253791781142354,
        "2s5s Spread_dist_ma_10d": 0.008466863073408604,
        "5s30s Spread_vol_10d": 0.0026214909739792347,
        "3-Year_pct_change_5d": 0.0035880128853023052,
        "5s30s Spread_change_10d": 0.002950033638626337,
        "5s30s Spread_pct_change_5d": 0.003805165644735098,
        "1-Year_rsi_63d": 0.0030485824681818485,
        "20-Year_vol_21d": 0.00391995208337903,
        "3m10y Spread_zscore_5d": 0.004023692570626736,
        "6-Month_rsi_5d": 0.0020735766738653183,
        "5s30s Spread_rsi_10d": 0.003014217596501112,
        "2-Year_dist_ma_63d": 0.004482257179915905,
        "5-Year_vol_5d": 0.003102512564510107,
        "2s5s Spread_change_1d": 0.00543232262134552,
        "2-Year_change_1d": 0.00502596702426672,
        "2-Year_change_10d": 0.004137841518968344,
        "2-Year_rsi_21d": 0.004617311060428619,
        "10s30s Spread_dist_ma_21d": 0.003682465059682727,
        "3m10y Spread_rsi_5d": 0.002818579552695155,
        "2s5s Spread_dist_ma_63d": 0.00605257973074913,
        "3m10y Spread_zscore_10d": 0.003708230797201395,
        "2s10s Spread_zscore_126d": 0.003130834549665451,
        "is_day_before_holiday": 0.0,
        "2s5s Spread_pct_change_63d": 0.0044927773997187614,
        "3m10y Spread_rsi_10d": 0.0015891768271103501,
        "3-Month_dist_ma_10d": 0.0036149020306766033,
        "10s30s Spread_zscore_5d": 0.005326530430465937,
        "10s30s Spread_dist_ma_10d": 0.009119058027863503,
        "5-Year_vol_10d": 0.001520992023870349,
        "6-Month_zscore_10d": 0.0028841965831816196,
        "6-Month_rsi_63d": 0.004005021415650845,
        "2s10s Spread_zscore_63d": 0.0038088455330580473,
        "2s10s Spread_pct_change_63d": 0.0034591525327414274,
        "2s5s Spread_zscore_63d": 0.004333332180976868,
        "2-Year_pct_change_5d": 0.004458611831068993,
        "3-Month_zscore_10d": 0.002607117872685194,
        "10s30s Spread_vol_252d": 0.0027695954777300358,
        "2s5s Spread_zscore_126d": 0.002097576856613159,
        "2-Year_zscore_63d": 0.007595863193273544,
        "10s30s Spread_dist_ma_5d": 0.005294204689562321,
        "2s5s Spread_rsi_5d": 0.0030799165833741426,
        "3-Year_rsi_10d": 0.0026997129898518324,
        "3-Year_rsi_5d": 0.0026078459341078997,
        "2-Year_zscore_5d": 0.0023393461015075445,
        "5s30s Spread_zscore_63d": 0.0049712276086211205,
        "5s30s Spread_zscore_21d": 0.001439542742446065,
        "3m10y Spread_vol_21d": 0.004513484425842762,
        "5s30s Spread_zscore_10d": 0.0020313607528805733,
        "10s30s Spread_pct_change_252d": 0.0038251425139606,
        "10s30s Spread_pct_change_1d": 0.004276897758245468,
        "2s10s Spread_vol_21d": 0.004935004748404026,
        "6-Month_zscore_5d": 0.001577626564539969,
        "3m10y Spread_change_10d": 0.0031479964964091778,
        "5s30s Spread_change_126d": 0.0031969938427209854,
        "3m10y Spread_vol_252d": 0.002469143131747842,
        "10s30s Spread_change_5d": 0.0011378980707377195,
        "5s30s Spread_vol_5d": 0.0019051574636250734,
        "6-Month_rsi_21d": 0.0021049894858151674,
        "1-Year_rsi_10d": 0.0028937775641679764,
        "5-Year_zscore_10d": 0.0027588256634771824,
        "3-Year_pct_change_10d": 0.003810744034126401,
        "2s10s Spread_rsi_5d": 0.00297338655218482,
        "2-Year_change_5d": 0.007447114679962397,
        "2-Year_zscore_10d": 0.003160304157063365,
        "10s30s Spread_vol_63d": 0.005950841587036848,
        "10s30s Spread_pct_change_10d": 0.0038750271778553724,
        "1-Year_change_1d": 0.0017619032878428698,
        "3m10y Spread_dist_ma_10d": 0.00960453413426876,
        "2s5s Spread_zscore_5d": 0.0021986563224345446,
        "2s5s Spread_change_126d": 0.001827838597819209,
        "2s5s Spread_zscore_10d": 0.005002559162676334,
        "2-Year_rsi_5d": 0.0028044916689395905,
        "3-Month_vol_21d": 0.004264687653630972
    },
    "train_loss": null,
    "val_loss": null,
    "best_epoch": null,
    "training_time": null,
    "device": "cuda",
    "timestamp": "2025-04-11T13:23:00.461252"
}