{
    "spread": "2s10s",
    "prediction_type": "next_day",
    "model_type": "lstm",
    "num_features": 271,
    "selected_features": [
        "10s30s Spread_dist_ma_126d",
        "2-Year_zscore_63d",
        "2-Year_zscore_5d",
        "3m10y Spread_pct_change_21d",
        "5s30s Spread_change_1d",
        "2s10s Spread_zscore_126d",
        "5s30s Spread_vol_63d",
        "6-Month_dist_ma_5d",
        "10s30s Spread_change_5d",
        "5s30s Spread_dist_ma_126d",
        "10s30s Spread_vol_5d",
        "3-Month_vol_5d",
        "2s5s Spread_vol_126d",
        "5s30s Spread_zscore_5d",
        "2s10s Spread_change_5d",
        "2s5s Spread_zscore_10d",
        "3-Month_pct_change_10d",
        "3-Year_rsi_10d",
        "2-Year_dist_ma_63d",
        "5s30s Spread_dist_ma_63d",
        "3-Month_zscore_21d",
        "5s30s Spread_pct_change_1d",
        "5-Year_vol_5d",
        "10s30s Spread_rsi_10d",
        "5-Year_vol_10d",
        "2s10s Spread_rsi_21d",
        "5-Year_pct_change_21d",
        "3-Month_vol_63d",
        "5s30s Spread_pct_change_10d",
        "1-Year_dist_ma_21d",
        "10s30s Spread_dist_ma_252d",
        "1-Year_zscore_5d",
        "2s5s Spread_zscore_126d",
        "10s30s Spread_vol_21d",
        "5s30s Spread_dist_ma_10d",
        "2s5s Spread_pct_change_10d",
        "3m10y Spread_zscore_63d",
        "6-Month_pct_change_1d",
        "5s30s Spread_pct_change_63d",
        "5s30s Spread_vol_10d",
        "5-Year_zscore_10d",
        "3-Year_change_1d",
        "3-Month_zscore_10d",
        "1-Year_pct_change_5d",
        "3-Month_vol_10d",
        "2-Year_rsi_21d",
        "1-Year_zscore_21d",
        "1-Year_vol_5d",
        "5s30s Spread_pct_change_5d",
        "2s5s Spread_rsi_21d",
        "is_day_before_holiday",
        "3-Month_vol_126d",
        "5s30s Spread_zscore_252d",
        "3m10y Spread_pct_change_10d",
        "1-Year_dist_ma_10d",
        "2-Year_zscore_126d",
        "3m10y Spread_rsi_21d",
        "2s5s Spread_dist_ma_5d",
        "2-Year_zscore_21d",
        "3-Year_pct_change_63d",
        "day_of_month",
        "1-Year_zscore_126d",
        "5s30s Spread_change_21d",
        "10s30s Spread_dist_ma_21d",
        "1-Year_pct_change_1d",
        "10s30s Spread_rsi_5d",
        "2-Year_vol_21d",
        "6-Month_zscore_63d",
        "5-Year_zscore_5d",
        "5-Year_pct_change_10d",
        "yield_pc3_curvature",
        "3-Month_zscore_252d",
        "3-Year_pct_change_10d",
        "2-Year_rsi_10d",
        "2s10s Spread_dist_ma_5d",
        "10s30s Spread_dist_ma_10d",
        "5-Year_change_1d",
        "3-Year_rsi_5d",
        "3-Year_zscore_5d",
        "2s5s Spread_vol_21d",
        "3-Month_rsi_63d",
        "5s30s Spread_change_10d",
        "6-Month_zscore_10d",
        "3-Year_pct_change_21d",
        "2-Year_dist_ma_5d",
        "3-Month_pct_change_1d",
        "2s10s Spread_pct_change_63d",
        "3-Month_dist_ma_21d",
        "3-Month_zscore_63d",
        "yield_pc2_slope",
        "1-Year_vol_10d",
        "1-Year_zscore_10d",
        "6-Month_zscore_21d",
        "3-Month_rsi_21d",
        "5-Year_pct_change_5d",
        "2s10s Spread_vol_5d",
        "5-Year_rsi_10d",
        "2s10s Spread_zscore_10d",
        "10s30s Spread_zscore_63d",
        "2s10s Spread_pct_change_1d",
        "3m10y Spread_zscore_10d",
        "5s30s Spread_change_5d",
        "6-Month_zscore_126d",
        "2-Year_rsi_63d",
        "2-Year_pct_change_5d",
        "5s30s Spread_pct_change_126d",
        "3m10y Spread_change_5d",
        "2-Year_zscore_10d",
        "10s30s Spread_dist_ma_5d",
        "2s5s Spread_vol_10d",
        "3m10y Spread_pct_change_1d",
        "2-Year_change_5d",
        "3m10y Spread_pct_change_5d",
        "2s5s Spread_zscore_5d",
        "3m10y Spread_change_21d",
        "10s30s Spread_pct_change_1d",
        "2-Year_pct_change_1d",
        "5s30s Spread_pct_change_21d",
        "5-Year_vol_126d",
        "5s30s Spread_zscore_126d",
        "6-Month_zscore_5d",
        "3m10y Spread_change_10d",
        "2-Year_pct_change_10d",
        "3-Year_pct_change_5d",
        "2s5s Spread_pct_change_1d",
        "3-Year_pct_change_126d",
        "3m10y Spread_dist_ma_63d",
        "3-Year_zscore_21d",
        "3m10y Spread_zscore_5d",
        "3-Month_dist_ma_10d",
        "2s10s Spread_rsi_5d",
        "2s5s Spread_vol_5d",
        "10s30s Spread_vol_126d",
        "10s30s Spread_zscore_5d",
        "2-Year_pct_change_21d",
        "2s10s Spread_change_1d",
        "10s30s Spread_dist_ma_63d",
        "2s5s Spread_dist_ma_10d",
        "3m10y Spread_dist_ma_5d",
        "3m10y Spread_zscore_21d",
        "2-Year_change_10d",
        "6-Month_vol_21d",
        "2s5s Spread_dist_ma_252d",
        "2s10s Spread_dist_ma_21d",
        "2s10s Spread_vol_63d",
        "3m10y Spread_vol_21d",
        "5s30s Spread_zscore_63d",
        "10s30s Spread_pct_change_10d",
        "1-Year_rsi_5d",
        "2s5s Spread_change_63d",
        "6-Month_pct_change_10d",
        "5s30s Spread_vol_21d",
        "3-Month_dist_ma_5d",
        "5s30s Spread_zscore_10d",
        "5-Year_vol_63d",
        "2s10s Spread_zscore_21d",
        "5-Year_pct_change_1d",
        "3-Year_pct_change_1d",
        "2s5s Spread_dist_ma_21d",
        "2-Year_rsi_126d",
        "6-Month_pct_change_21d",
        "5s30s Spread_rsi_63d",
        "2s10s Spread_rsi_10d",
        "2s10s Spread_vol_21d",
        "2s5s Spread_change_5d",
        "2s5s Spread_zscore_21d",
        "1-Year_vol_63d",
        "6-Month_zscore_252d",
        "2s5s Spread_rsi_10d",
        "2s5s Spread_change_252d",
        "3-Month_rsi_10d",
        "3m10y Spread_zscore_126d",
        "2s5s Spread_rsi_5d",
        "3-Month_zscore_5d",
        "3-Month_pct_change_5d",
        "5s30s Spread_dist_ma_5d",
        "2s10s Spread_change_63d",
        "2s10s Spread_change_21d",
        "3m10y Spread_rsi_10d",
        "5s30s Spread_vol_5d",
        "6-Month_dist_ma_10d",
        "2s10s Spread_change_10d",
        "6-Month_vol_10d",
        "5s30s Spread_rsi_5d",
        "2s10s Spread_pct_change_21d",
        "20-Year_vol_5d",
        "2s10s Spread_vol_10d",
        "2-Year_dist_ma_21d",
        "3m10y Spread_rsi_5d",
        "1-Year_pct_change_63d",
        "20-Year_vol_21d",
        "3-Year_zscore_10d",
        "3m10y Spread_dist_ma_10d",
        "3-Month_zscore_126d",
        "3m10y Spread_zscore_252d",
        "2s5s Spread_zscore_63d",
        "6-Month_vol_5d",
        "2s5s Spread_change_1d",
        "5s30s Spread_rsi_21d",
        "3m10y Spread_pct_change_126d",
        "1-Year_pct_change_21d",
        "2s5s Spread_pct_change_5d",
        "5s30s Spread_rsi_10d",
        "10s30s Spread_rsi_63d",
        "10s30s Spread_pct_change_5d",
        "3-Month_vol_21d",
        "6-Month_rsi_10d",
        "3m10y Spread_vol_5d",
        "2-Year_vol_10d",
        "2s5s Spread_dist_ma_63d",
        "1-Year_zscore_63d",
        "2-Year_rsi_5d",
        "3-Year_dist_ma_5d",
        "2-Year_change_1d",
        "20-Year_vol_10d",
        "1-Year_rsi_10d",
        "3m10y Spread_pct_change_63d",
        "10s30s Spread_vol_63d",
        "6-Month_pct_change_5d",
        "2s5s Spread_vol_63d",
        "2s5s Spread_change_126d",
        "3-Month_rsi_5d",
        "2-Year_dist_ma_10d",
        "6-Month_rsi_5d",
        "10s30s Spread_pct_change_63d",
        "10s30s Spread_vol_10d",
        "10s30s Spread_change_21d",
        "3-Month_pct_change_21d",
        "3m10y Spread_dist_ma_21d",
        "5s30s Spread_vol_126d",
        "2-Year_vol_63d",
        "3m10y Spread_vol_252d",
        "day_of_week",
        "3-Year_vol_5d",
        "2s10s Spread_pct_change_10d",
        "6-Month_rsi_21d",
        "6-Month_dist_ma_21d",
        "1-Year_vol_21d",
        "2s10s Spread_vol_126d",
        "5-Year_vol_21d",
        "1-Year_rsi_21d",
        "1-Year_change_1d",
        "3m10y Spread_vol_126d",
        "2s10s Spread_zscore_5d",
        "1-Year_dist_ma_5d",
        "2s5s Spread_zscore_252d",
        "5s30s Spread_dist_ma_21d",
        "2s10s Spread_pct_change_5d",
        "1-Year_pct_change_10d",
        "10s30s Spread_rsi_21d",
        "2s5s Spread_pct_change_63d",
        "2s5s Spread_pct_change_21d",
        "2s5s Spread_change_21d",
        "10s30s Spread_pct_change_21d",
        "2s10s Spread_dist_ma_252d",
        "5s30s Spread_change_126d",
        "3m10y Spread_change_1d",
        "2s5s Spread_dist_ma_126d",
        "10s30s Spread_zscore_21d",
        "2s10s Spread_dist_ma_63d",
        "2s5s Spread_vol_252d",
        "3m10y Spread_vol_10d",
        "2-Year_change_21d",
        "5s30s Spread_zscore_21d",
        "3m10y Spread_vol_63d",
        "2-Year_vol_5d",
        "2s10s Spread_dist_ma_10d",
        "2s10s Spread_zscore_63d",
        "5-Year_rsi_5d",
        "1-Year_change_21d",
        "10s30s Spread_zscore_10d"
    ],
    "mse": 3.8110086917877197,
    "accuracy": null,
    "f1": null,
    "roc_auc": null,
    "feature_importance": {},
    "train_loss": 0.013826373487476801,
    "val_loss": 0.012444907072414127,
    "best_epoch": null,
    "training_time": null,
    "device": "cuda",
    "timestamp": "2025-04-11T10:02:06.456744"
}